LICENSE
README.md
setup.py
aitts_maker/__init__.py
aitts_maker/cli.py
aitts_maker/core.py
aitts_maker.egg-info/PKG-INFO
aitts_maker.egg-info/SOURCES.txt
aitts_maker.egg-info/dependency_links.txt
aitts_maker.egg-info/entry_points.txt
aitts_maker.egg-info/requires.txt
aitts_maker.egg-info/top_level.txt