Metadata-Version: 2.1
Name: aitts-maker
Version: 0.1.0
Summary: AI and standard TTS voice generator using ttsmp3.com (via scraping)
Home-page: https://github.com/Dot-ser/aitts-maker
Author: DOT-007
Author-email: alosiousbenny7@gmail.com
License: UNKNOWN
Platform: UNKNOWN
Classifier: Programming Language :: Python :: 3
Classifier: License :: OSI Approved :: MIT License
Classifier: Operating System :: OS Independent
Classifier: Topic :: Multimedia :: Sound/Audio :: Speech
Requires-Python: >=3.6
License-File: LICENSE
